fn/__init__.py
fn/base.py
fn/core.py
fn/dialect/__init__.py
fn/dialect/click/__init__.py
fn/dialect/click/adapter.py
fn/dialect/click/config.py
fn/standard/__init__.py
fn/standard/adapter.py
fn/standard/config.py
fn/type.py
ifn-0.1.3.dist-info/LICENSE.txt
ifn-0.1.3.dist-info/WHEEL
ifn-0.1.3.dist-info/METADATA
ifn-0.1.3.dist-info/RECORD
